pearcey/__init__.py
pearcey/pearcey.py
pearcey-0.1.1.dist-info/METADATA
pearcey-0.1.1.dist-info/WHEEL
pearcey-0.1.1.dist-info/top_level.txt
pearcey-0.1.1.dist-info/RECORD
