Metadata-Version: 2.1
Name: pearcey
Version: 0.1.1
Summary: A python package to compute the Pearcey function/integral in catastrophe optics
Classifier: License :: OSI Approved :: MIT License
Requires-Python: >=3.7
Requires-Dist: numpy
Requires-Dist: scipy
